{
    "fluentMethods": true,
    "clientRootFolder": "",
    "relationships": [],
    "fields": [
        {
            "fieldName": "name",
            "fieldType": "String",
            "fieldValidateRules": [
                "required"
            ]
        }
    ],
    "changelogDate": "20200426175527",
    "dto": "no",
    "searchEngine": false,
    "service": "no",
    "entityTableName": "bidder",
    "databaseType": "sql",
    "readOnly": false,
    "jpaMetamodelFiltering": false,
    "pagination": "no"
}
